c8_source_c8collection/__init__.py
c8_source_c8collection/client.py
c8_source_c8collection-0.0.10.dist-info/entry_points.txt
c8_source_c8collection-0.0.10.dist-info/WHEEL
c8_source_c8collection-0.0.10.dist-info/METADATA
c8_source_c8collection-0.0.10.dist-info/RECORD
