Metadata-Version: 2.1
Name: c8-source-c8collection
Version: 0.0.10
Summary: Pipelinewise tap for reading from C8 Collections
License: Apache-2.0
Keywords: ELT,Connectors,Workflows,Macrometa,C8Collection,Tap
Author: Macrometa
Author-email: info@macrometa.com
Requires-Python: >=3.8.1,<3.11
Classifier: License :: OSI Approved :: Apache Software License
Classifier: Operating System :: OS Independent
Classifier: Programming Language :: Python :: 3
Classifier: Programming Language :: Python :: 3.9
Classifier: Programming Language :: Python :: 3.10
Classifier: Programming Language :: Python :: 3
Classifier: Programming Language :: Python :: 3.9
Requires-Dist: c8connector (>=0,<1)
Requires-Dist: chardet (==4.0.0)
Requires-Dist: idna (==2.10)
Requires-Dist: numpy (==1.21.6)
Requires-Dist: pandas (==1.3.5)
Requires-Dist: pipelinewise-singer-python (==1.2.0)
Requires-Dist: pulsar-client (==2.10.1)
Requires-Dist: pyC8 (==0.17.3)
Requires-Dist: requests (==2.25.1)
Requires-Dist: websocket-client (==0.57.0)
Project-URL: Bug Tracker, https://github.com/Macrometacorp/c8-source-c8collection/issues
